thumbnail/__init__.py
thumbnail/mimedb.json
thumbnail/thumbnail.py
thumbnail-1.5.dist-info/LICENSE
thumbnail-1.5.dist-info/METADATA
thumbnail-1.5.dist-info/WHEEL
thumbnail-1.5.dist-info/top_level.txt
thumbnail-1.5.dist-info/RECORD
