Metadata-Version: 2.1
Name: thumbnail
Version: 1.5
Summary: Thumbnail/Preview generator for 450 different filetypes in python.
Home-page: https://github.com/anshulkharb/thumbnail
Author: Anshul Kharb
Author-email: hey@anshulkharb.com
License: UNKNOWN
Platform: UNKNOWN
Classifier: Programming Language :: Python :: 3
Classifier: License :: OSI Approved :: MIT License
Classifier: Operating System :: OS Independent
Requires-Python: >=3.6
